[
  {
    "name": "AayushSaini101",
    "isVotedInLast3Months": true,
    "lastClosedVoteTime": "2024-06-15T05:08:46.147Z"
  },
  {
    "name": "Mayaleeeee",
    "isVotedInLast3Months": "Member doesn't give vote to any voting process",
    "lastClosedVoteTime": "2024-06-15T05:08:46.147Z"
  },
  {
    "name": "aayushmau5",
    "isVotedInLast3Months": "Member doesn't give vote to any voting process",
    "lastClosedVoteTime": "2024-06-15T05:08:46.147Z"
  },
  {
    "name": "imabp",
    "isVotedInLast3Months": "Member doesn't give vote to any voting process",
    "lastClosedVoteTime": "2024-06-15T05:08:46.147Z"
  },
  {
    "name": "akshatnema",
    "isVotedInLast3Months": "Member doesn't give vote to any voting process",
    "lastClosedVoteTime": "2024-06-15T05:08:46.147Z"
  },
  {
    "name": "anshgoyalevil",
    "isVotedInLast3Months": "Member doesn't give vote to any voting process",
    "lastClosedVoteTime": "2024-06-15T05:08:46.147Z"
  },
  {
    "name": "anandsunderraman",
    "isVotedInLast3Months": "Member doesn't give vote to any voting process",
    "lastClosedVoteTime": "2024-06-15T05:08:46.147Z"
  },
  {
    "name": "Shurtu-gal",
    "isVotedInLast3Months": "Member doesn't give vote to any voting process",
    "lastClosedVoteTime": "2024-06-15T05:08:46.147Z"
  },
  {
    "name": "cameronrushton",
    "isVotedInLast3Months": "Member doesn't give vote to any voting process",
    "lastClosedVoteTime": "2024-06-15T05:08:46.147Z"
  },
  {
    "name": "dalelane",
    "isVotedInLast3Months": "Member doesn't give vote to any voting process",
    "lastClosedVoteTime": "2024-06-15T05:08:46.147Z"
  },
  {
    "name": "emilianozublena",
    "isVotedInLast3Months": "Member doesn't give vote to any voting process",
    "lastClosedVoteTime": "2024-06-15T05:08:46.147Z"
  },
  {
    "name": "fmvilas",
    "isVotedInLast3Months": "Member doesn't give vote to any voting process",
    "lastClosedVoteTime": "2024-06-15T05:08:46.147Z"
  },
  {
    "name": "geraldloeffler",
    "isVotedInLast3Months": "Member doesn't give vote to any voting process",
    "lastClosedVoteTime": "2024-06-15T05:08:46.147Z"
  },
  {
    "name": "jonaslagoni",
    "isVotedInLast3Months": "Member doesn't give vote to any voting process",
    "lastClosedVoteTime": "2024-06-15T05:08:46.147Z"
  },
  {
    "name": "khudadad414",
    "isVotedInLast3Months": "Member doesn't give vote to any voting process",
    "lastClosedVoteTime": "2024-06-15T05:08:46.147Z"
  },
  {
    "name": "lbroudoux",
    "isVotedInLast3Months": "Member doesn't give vote to any voting process",
    "lastClosedVoteTime": "2024-06-15T05:08:46.147Z"
  },
  {
    "name": "M3lkior",
    "isVotedInLast3Months": "Member doesn't give vote to any voting process",
    "lastClosedVoteTime": "2024-06-15T05:08:46.147Z"
  },
  {
    "name": "derberg",
    "isVotedInLast3Months": "Member doesn't give vote to any voting process",
    "lastClosedVoteTime": "2024-06-15T05:08:46.147Z"
  },
  {
    "name": "magicmatatjahu",
    "isVotedInLast3Months": "Member doesn't give vote to any voting process",
    "lastClosedVoteTime": "2024-06-15T05:08:46.147Z"
  },
  {
    "name": "acethecreator",
    "isVotedInLast3Months": "Member doesn't give vote to any voting process",
    "lastClosedVoteTime": "2024-06-15T05:08:46.147Z"
  },
  {
    "name": "damaru-inc",
    "isVotedInLast3Months": "Member doesn't give vote to any voting process",
    "lastClosedVoteTime": "2024-06-15T05:08:46.147Z"
  },
  {
    "name": "mcturco",
    "isVotedInLast3Months": "Member doesn't give vote to any voting process",
    "lastClosedVoteTime": "2024-06-15T05:08:46.147Z"
  },
  {
    "name": "nektariosfifes",
    "isVotedInLast3Months": "Member doesn't give vote to any voting process",
    "lastClosedVoteTime": "2024-06-15T05:08:46.147Z"
  },
  {
    "name": "pakisan",
    "isVotedInLast3Months": "Member doesn't give vote to any voting process",
    "lastClosedVoteTime": "2024-06-15T05:08:46.147Z"
  },
  {
    "name": "theschles",
    "isVotedInLast3Months": "Member doesn't give vote to any voting process",
    "lastClosedVoteTime": "2024-06-15T05:08:46.147Z"
  },
  {
    "name": "princerajpoot20",
    "isVotedInLast3Months": "Member doesn't give vote to any voting process",
    "lastClosedVoteTime": "2024-06-15T05:08:46.147Z"
  },
  {
    "name": "rcoppen",
    "isVotedInLast3Months": "Member doesn't give vote to any voting process",
    "lastClosedVoteTime": "2024-06-15T05:08:46.147Z"
  },
  {
    "name": "Amzani",
    "isVotedInLast3Months": "Member doesn't give vote to any voting process",
    "lastClosedVoteTime": "2024-06-15T05:08:46.147Z"
  },
  {
    "name": "smoya",
    "isVotedInLast3Months": "Member doesn't give vote to any voting process",
    "lastClosedVoteTime": "2024-06-15T05:08:46.147Z"
  },
  {
    "name": "souvikns",
    "isVotedInLast3Months": "Member doesn't give vote to any voting process",
    "lastClosedVoteTime": "2024-06-15T05:08:46.147Z"
  },
  {
    "name": "alequetzalli",
    "isVotedInLast3Months": "Member doesn't give vote to any voting process",
    "lastClosedVoteTime": "2024-06-15T05:08:46.147Z"
  },
  {
    "name": "bolt04",
    "isVotedInLast3Months": "Member doesn't give vote to any voting process",
    "lastClosedVoteTime": "2024-06-15T05:08:46.147Z"
  },
  {
    "name": "dan-r",
    "isVotedInLast3Months": "Member doesn't give vote to any voting process",
    "lastClosedVoteTime": "2024-06-15T05:08:46.147Z"
  },
  {
    "name": "kieranm1999",
    "isVotedInLast3Months": "Member doesn't give vote to any voting process",
    "lastClosedVoteTime": "2024-06-15T05:08:46.147Z"
  },
  {
    "name": "jefflufc",
    "isVotedInLast3Months": "Member doesn't give vote to any voting process",
    "lastClosedVoteTime": "2024-06-15T05:08:46.147Z"
  },
  {
    "name": "lewis-relph",
    "isVotedInLast3Months": "Member doesn't give vote to any voting process",
    "lastClosedVoteTime": "2024-06-15T05:08:46.147Z"
  },
  {
    "name": "tenischev",
    "isVotedInLast3Months": "Member doesn't give vote to any voting process",
    "lastClosedVoteTime": "2024-06-15T05:08:46.147Z"
  },
  {
    "name": "samridhi-98",
    "isVotedInLast3Months": "Member doesn't give vote to any voting process",
    "lastClosedVoteTime": "2024-06-15T05:08:46.147Z"
  },
  {
    "name": "ron-debajyoti",
    "isVotedInLast3Months": "Member doesn't give vote to any voting process",
    "lastClosedVoteTime": "2024-06-15T05:08:46.147Z"
  },
  {
    "name": "ivangsa",
    "isVotedInLast3Months": "Member doesn't give vote to any voting process",
    "lastClosedVoteTime": "2024-06-15T05:08:46.147Z"
  },
  {
    "name": "florence-njeri",
    "isVotedInLast3Months": "Member doesn't give vote to any voting process",
    "lastClosedVoteTime": "2024-06-15T05:08:46.147Z"
  },
  {
    "name": "whitlockjc",
    "isVotedInLast3Months": "Member doesn't give vote to any voting process",
    "lastClosedVoteTime": "2024-06-15T05:08:46.147Z"
  },
  {
    "name": "char0n",
    "isVotedInLast3Months": "Member doesn't give vote to any voting process",
    "lastClosedVoteTime": "2024-06-15T05:08:46.147Z"
  },
  {
    "name": "visualbean",
    "isVotedInLast3Months": "Member doesn't give vote to any voting process",
    "lastClosedVoteTime": "2024-06-15T05:08:46.147Z"
  },
  {
    "name": "kennethaasan",
    "isVotedInLast3Months": "Member doesn't give vote to any voting process",
    "lastClosedVoteTime": "2024-06-15T05:08:46.147Z"
  },
  {
    "name": "greenrover",
    "isVotedInLast3Months": "Member doesn't give vote to any voting process",
    "lastClosedVoteTime": "2024-06-15T05:08:46.147Z"
  },
  {
    "name": "thulieblack",
    "isVotedInLast3Months": "Member doesn't give vote to any voting process",
    "lastClosedVoteTime": "2024-06-15T05:08:46.147Z"
  },
  {
    "name": "devilkiller-ag",
    "isVotedInLast3Months": "Member doesn't give vote to any voting process",
    "lastClosedVoteTime": "2024-06-15T05:08:46.147Z"
  },
  {
    "name": "sambhavgupta0705",
    "isVotedInLast3Months": "Member doesn't give vote to any voting process",
    "lastClosedVoteTime": "2024-06-15T05:08:46.147Z"
  }
]